{
    "openapi": "3.0.0",
    "info": {
        "title": "Catch Me API",
        "description": "Social proximity app API for connecting nearby people",
        "version": "1.0.0"
    },
    "paths": {
        "/api/auth/register": {
            "post": {
                "tags": [
                    "Authentication"
                ],
                "summary": "Register a new user",
                "operationId": "c7bb21a0d87049e161b8e4c9b0d909f2",
                "requestBody": {
                    "required": true,
                    "content": {
                        "application/json": {
                            "schema": {
                                "required": [
                                    "name",
                                    "phone",
                                    "password",
                                    "gender"
                                ],
                                "properties": {
                                    "name": {
                                        "type": "string",
                                        "example": "John Doe"
                                    },
                                    "phone": {
                                        "type": "string",
                                        "example": "+33612345678"
                                    },
                                    "password": {
                                        "type": "string",
                                        "example": "password123"
                                    },
                                    "gender": {
                                        "type": "string",
                                        "enum": [
                                            "male",
                                            "female",
                                            "other"
                                        ]
                                    },
                                    "email": {
                                        "type": "string",
                                        "example": "john@example.com"
                                    },
                                    "language": {
                                        "type": "string",
                                        "enum": [
                                            "fr",
                                            "ar"
                                        ]
                                    }
                                },
                                "type": "object"
                            }
                        }
                    }
                },
                "responses": {
                    "201": {
                        "description": "User registered successfully"
                    },
                    "422": {
                        "description": "Validation error"
                    }
                }
            }
        },
        "/api/auth/login": {
            "post": {
                "tags": [
                    "Authentication"
                ],
                "summary": "Login user",
                "operationId": "dd51a484b7fa0f97c7680fdbde14cf5f",
                "requestBody": {
                    "required": true,
                    "content": {
                        "application/json": {
                            "schema": {
                                "required": [
                                    "phone",
                                    "password"
                                ],
                                "properties": {
                                    "phone": {
                                        "type": "string"
                                    },
                                    "password": {
                                        "type": "string"
                                    },
                                    "fcm_token": {
                                        "type": "string"
                                    }
                                },
                                "type": "object"
                            }
                        }
                    }
                },
                "responses": {
                    "200": {
                        "description": "Login successful"
                    },
                    "401": {
                        "description": "Invalid credentials"
                    }
                }
            }
        },
        "/api/auth/logout": {
            "post": {
                "tags": [
                    "Authentication"
                ],
                "summary": "Logout user",
                "operationId": "df9bdc6c7a6d9f20b983526b2ec0f698",
                "responses": {
                    "200": {
                        "description": "Logout successful"
                    }
                },
                "security": [
                    {
                        "bearerAuth": []
                    }
                ]
            }
        },
        "/api/auth/user": {
            "get": {
                "tags": [
                    "Authentication"
                ],
                "summary": "Get authenticated user",
                "operationId": "015ae3b99f0678ec8fe0a02409751660",
                "responses": {
                    "200": {
                        "description": "User data retrieved"
                    }
                },
                "security": [
                    {
                        "bearerAuth": []
                    }
                ]
            }
        },
        "/api/auth/social": {
            "post": {
                "tags": [
                    "Authentication"
                ],
                "summary": "Social authentication (Google/Apple)",
                "operationId": "d4b379ec62c202bf53e09aab3d357729",
                "requestBody": {
                    "required": true,
                    "content": {
                        "application/json": {
                            "schema": {
                                "required": [
                                    "provider",
                                    "provider_id",
                                    "name"
                                ],
                                "properties": {
                                    "provider": {
                                        "type": "string",
                                        "enum": [
                                            "google",
                                            "apple"
                                        ]
                                    },
                                    "provider_id": {
                                        "type": "string"
                                    },
                                    "name": {
                                        "type": "string"
                                    },
                                    "email": {
                                        "type": "string"
                                    },
                                    "phone": {
                                        "type": "string"
                                    },
                                    "gender": {
                                        "type": "string"
                                    }
                                },
                                "type": "object"
                            }
                        }
                    }
                },
                "responses": {
                    "200": {
                        "description": "Login successful"
                    }
                }
            }
        },
        "/api/block": {
            "post": {
                "tags": [
                    "Block"
                ],
                "summary": "Block a user (Safety Feature)",
                "operationId": "780b368cbd957d092006a1ac81ec0792",
                "requestBody": {
                    "required": true,
                    "content": {
                        "application/json": {
                            "schema": {
                                "required": [
                                    "user_id"
                                ],
                                "properties": {
                                    "user_id": {
                                        "description": "ID of user to block",
                                        "type": "integer"
                                    },
                                    "reason": {
                                        "description": "Optional reason for blocking",
                                        "type": "string"
                                    }
                                },
                                "type": "object"
                            }
                        }
                    }
                },
                "responses": {
                    "200": {
                        "description": "User blocked successfully",
                        "content": {
                            "application/json": {
                                "schema": {
                                    "properties": {
                                        "message": {
                                            "type": "string",
                                            "example": "User blocked successfully"
                                        }
                                    },
                                    "type": "object"
                                }
                            }
                        }
                    },
                    "400": {
                        "description": "Cannot block yourself or already blocked"
                    },
                    "422": {
                        "description": "Validation error"
                    }
                },
                "security": [
                    {
                        "bearerAuth": []
                    }
                ]
            }
        },
        "/api/block/{userId}": {
            "delete": {
                "tags": [
                    "Block"
                ],
                "summary": "Unblock a user",
                "operationId": "a8badffc25884f56cb9f4d9cfa2192a0",
                "parameters": [
                    {
                        "name": "userId",
                        "in": "path",
                        "description": "ID of user to unblock",
                        "required": true,
                        "schema": {
                            "type": "integer"
                        }
                    }
                ],
                "responses": {
                    "200": {
                        "description": "User unblocked successfully",
                        "content": {
                            "application/json": {
                                "schema": {
                                    "properties": {
                                        "message": {
                                            "type": "string",
                                            "example": "User unblocked successfully"
                                        }
                                    },
                                    "type": "object"
                                }
                            }
                        }
                    },
                    "404": {
                        "description": "User not blocked"
                    }
                },
                "security": [
                    {
                        "bearerAuth": []
                    }
                ]
            }
        },
        "/api/block/blocked-users": {
            "get": {
                "tags": [
                    "Block"
                ],
                "summary": "Get list of blocked users",
                "operationId": "bbefd0cd4e55f245a3ff08313f5d6b9e",
                "responses": {
                    "200": {
                        "description": "Blocked users retrieved",
                        "content": {
                            "application/json": {
                                "schema": {
                                    "properties": {
                                        "blocked_users": {
                                            "type": "array",
                                            "items": {
                                                "properties": {
                                                    "id": {
                                                        "type": "integer"
                                                    },
                                                    "blocker_id": {
                                                        "type": "integer"
                                                    },
                                                    "blocked_id": {
                                                        "type": "integer"
                                                    },
                                                    "reason": {
                                                        "type": "string"
                                                    },
                                                    "created_at": {
                                                        "type": "string",
                                                        "format": "date-time"
                                                    }
                                                },
                                                "type": "object"
                                            }
                                        }
                                    },
                                    "type": "object"
                                }
                            }
                        }
                    }
                },
                "security": [
                    {
                        "bearerAuth": []
                    }
                ]
            }
        },
        "/api/likes": {
            "post": {
                "tags": [
                    "Likes"
                ],
                "summary": "Send a like to another user",
                "operationId": "c751040220d9f402b4d7b23248dc0d1a",
                "requestBody": {
                    "required": true,
                    "content": {
                        "application/json": {
                            "schema": {
                                "required": [
                                    "to_user_id"
                                ],
                                "properties": {
                                    "to_user_id": {
                                        "type": "integer"
                                    }
                                },
                                "type": "object"
                            }
                        }
                    }
                },
                "responses": {
                    "201": {
                        "description": "Like sent"
                    },
                    "400": {
                        "description": "Bad request"
                    }
                },
                "security": [
                    {
                        "bearerAuth": []
                    }
                ]
            }
        },
        "/api/likes/{id}/accept": {
            "put": {
                "tags": [
                    "Likes"
                ],
                "summary": "Accept a like",
                "operationId": "cbe2525517d702b750d2f5a9e35a5d2f",
                "parameters": [
                    {
                        "name": "id",
                        "in": "path",
                        "required": true,
                        "schema": {
                            "type": "integer"
                        }
                    }
                ],
                "responses": {
                    "200": {
                        "description": "Like accepted"
                    }
                },
                "security": [
                    {
                        "bearerAuth": []
                    }
                ]
            }
        },
        "/api/likes/{id}/reject": {
            "put": {
                "tags": [
                    "Likes"
                ],
                "summary": "Reject a like",
                "operationId": "969f30f4b3f3bdf36ab31f8c75760cdd",
                "parameters": [
                    {
                        "name": "id",
                        "in": "path",
                        "required": true,
                        "schema": {
                            "type": "integer"
                        }
                    }
                ],
                "responses": {
                    "200": {
                        "description": "Like rejected"
                    }
                },
                "security": [
                    {
                        "bearerAuth": []
                    }
                ]
            }
        },
        "/api/likes/received": {
            "get": {
                "tags": [
                    "Likes"
                ],
                "summary": "Get received likes (pending)",
                "operationId": "77772c5ac06e3ac7a8ec2ed90528c27a",
                "responses": {
                    "200": {
                        "description": "Received likes retrieved"
                    }
                },
                "security": [
                    {
                        "bearerAuth": []
                    }
                ]
            }
        },
        "/api/matches": {
            "get": {
                "tags": [
                    "Likes"
                ],
                "summary": "Get all matches",
                "operationId": "14fe0bf789909e49ea0a01de2ebd2d8c",
                "responses": {
                    "200": {
                        "description": "Matches retrieved"
                    }
                },
                "security": [
                    {
                        "bearerAuth": []
                    }
                ]
            }
        },
        "/api/messages": {
            "post": {
                "tags": [
                    "Messages"
                ],
                "summary": "Send a message",
                "operationId": "01287e95cbd5fd2ac2b710dff31f1f0b",
                "requestBody": {
                    "required": true,
                    "content": {
                        "application/json": {
                            "schema": {
                                "required": [
                                    "receiver_id",
                                    "message"
                                ],
                                "properties": {
                                    "receiver_id": {
                                        "type": "integer"
                                    },
                                    "message": {
                                        "type": "string"
                                    }
                                },
                                "type": "object"
                            }
                        }
                    }
                },
                "responses": {
                    "201": {
                        "description": "Message sent"
                    }
                },
                "security": [
                    {
                        "bearerAuth": []
                    }
                ]
            }
        },
        "/api/messages/{userId}": {
            "get": {
                "tags": [
                    "Messages"
                ],
                "summary": "Get conversation with a user",
                "operationId": "6e46f7caca968eecb08e290a65f54b44",
                "parameters": [
                    {
                        "name": "userId",
                        "in": "path",
                        "required": true,
                        "schema": {
                            "type": "integer"
                        }
                    }
                ],
                "responses": {
                    "200": {
                        "description": "Messages retrieved"
                    }
                },
                "security": [
                    {
                        "bearerAuth": []
                    }
                ]
            }
        },
        "/api/conversations": {
            "get": {
                "tags": [
                    "Messages"
                ],
                "summary": "Get all conversations",
                "operationId": "c858b6fe5b914375cd95d0687aa7bbc0",
                "responses": {
                    "200": {
                        "description": "Conversations retrieved"
                    }
                },
                "security": [
                    {
                        "bearerAuth": []
                    }
                ]
            }
        },
        "/api/messages/{id}": {
            "delete": {
                "tags": [
                    "Messages"
                ],
                "summary": "Delete a message",
                "operationId": "134e1b5c53ab25645dc49c411becce4c",
                "parameters": [
                    {
                        "name": "id",
                        "in": "path",
                        "required": true,
                        "schema": {
                            "type": "integer"
                        }
                    }
                ],
                "responses": {
                    "200": {
                        "description": "Message deleted"
                    }
                },
                "security": [
                    {
                        "bearerAuth": []
                    }
                ]
            }
        },
        "/api/messages/{id}/delivered": {
            "post": {
                "tags": [
                    "Messages"
                ],
                "summary": "Mark message as delivered (two gray checkmarks)",
                "operationId": "b38a25192b6e597e969f8aef7646047f",
                "parameters": [
                    {
                        "name": "id",
                        "in": "path",
                        "required": true,
                        "schema": {
                            "type": "integer"
                        }
                    }
                ],
                "responses": {
                    "200": {
                        "description": "Message marked as delivered"
                    }
                },
                "security": [
                    {
                        "bearerAuth": []
                    }
                ]
            }
        },
        "/api/messages/{id}/read": {
            "post": {
                "tags": [
                    "Messages"
                ],
                "summary": "Mark message as read (two green checkmarks)",
                "operationId": "553d2d614d91f9532539581c8aef2106",
                "parameters": [
                    {
                        "name": "id",
                        "in": "path",
                        "required": true,
                        "schema": {
                            "type": "integer"
                        }
                    }
                ],
                "responses": {
                    "200": {
                        "description": "Message marked as read"
                    }
                },
                "security": [
                    {
                        "bearerAuth": []
                    }
                ]
            }
        },
        "/api/messages/bulk-delivered": {
            "post": {
                "tags": [
                    "Messages"
                ],
                "summary": "Mark multiple messages as delivered (for efficiency)",
                "operationId": "1b4a95ae66f1f77546bc0b07976e5005",
                "requestBody": {
                    "required": true,
                    "content": {
                        "application/json": {
                            "schema": {
                                "required": [
                                    "message_ids"
                                ],
                                "properties": {
                                    "message_ids": {
                                        "type": "array",
                                        "items": {
                                            "type": "integer"
                                        }
                                    }
                                },
                                "type": "object"
                            }
                        }
                    }
                },
                "responses": {
                    "200": {
                        "description": "Messages marked as delivered"
                    }
                },
                "security": [
                    {
                        "bearerAuth": []
                    }
                ]
            }
        },
        "/api/messages/bulk-read": {
            "post": {
                "tags": [
                    "Messages"
                ],
                "summary": "Mark multiple messages as read (for efficiency)",
                "operationId": "30df1f56ad4a306cc9f4c491a5e4bbf5",
                "requestBody": {
                    "required": true,
                    "content": {
                        "application/json": {
                            "schema": {
                                "required": [
                                    "message_ids"
                                ],
                                "properties": {
                                    "message_ids": {
                                        "type": "array",
                                        "items": {
                                            "type": "integer"
                                        }
                                    }
                                },
                                "type": "object"
                            }
                        }
                    }
                },
                "responses": {
                    "200": {
                        "description": "Messages marked as read"
                    }
                },
                "security": [
                    {
                        "bearerAuth": []
                    }
                ]
            }
        },
        "/api/reports": {
            "get": {
                "tags": [
                    "Reports"
                ],
                "summary": "Get user's reports",
                "operationId": "e186d3063570cba94ceb7da8bed91cad",
                "responses": {
                    "200": {
                        "description": "Reports retrieved"
                    }
                },
                "security": [
                    {
                        "bearerAuth": []
                    }
                ]
            },
            "post": {
                "tags": [
                    "Reports"
                ],
                "summary": "Report a user",
                "operationId": "6210cd22079fc586578fb64a7f6617fb",
                "requestBody": {
                    "required": true,
                    "content": {
                        "application/json": {
                            "schema": {
                                "required": [
                                    "reported_user_id",
                                    "reason"
                                ],
                                "properties": {
                                    "reported_user_id": {
                                        "type": "integer"
                                    },
                                    "reason": {
                                        "type": "string"
                                    }
                                },
                                "type": "object"
                            }
                        }
                    }
                },
                "responses": {
                    "201": {
                        "description": "Report submitted"
                    }
                },
                "security": [
                    {
                        "bearerAuth": []
                    }
                ]
            }
        },
        "/api/user/profile": {
            "put": {
                "tags": [
                    "User"
                ],
                "summary": "Update user profile",
                "operationId": "f5dfce3753e793253c65d12b593248a3",
                "requestBody": {
                    "content": {
                        "application/json": {
                            "schema": {
                                "properties": {
                                    "name": {
                                        "type": "string"
                                    },
                                    "bio": {
                                        "type": "string"
                                    },
                                    "gender": {
                                        "type": "string"
                                    },
                                    "language": {
                                        "type": "string"
                                    },
                                    "is_visible": {
                                        "type": "boolean"
                                    }
                                },
                                "type": "object"
                            }
                        }
                    }
                },
                "responses": {
                    "200": {
                        "description": "Profile updated"
                    }
                },
                "security": [
                    {
                        "bearerAuth": []
                    }
                ]
            }
        },
        "/api/user/profile-image": {
            "post": {
                "tags": [
                    "User"
                ],
                "summary": "Upload profile image",
                "operationId": "cbba0217d50e9414ce258ab6520eede5",
                "requestBody": {
                    "content": {
                        "multipart/form-data": {
                            "schema": {
                                "properties": {
                                    "image": {
                                        "type": "string",
                                        "format": "binary"
                                    }
                                },
                                "type": "object"
                            }
                        }
                    }
                },
                "responses": {
                    "200": {
                        "description": "Image uploaded"
                    }
                },
                "security": [
                    {
                        "bearerAuth": []
                    }
                ]
            }
        },
        "/api/user/location": {
            "post": {
                "tags": [
                    "User"
                ],
                "summary": "Update user location",
                "operationId": "ff95e74d602822ede448505bad858dd8",
                "requestBody": {
                    "required": true,
                    "content": {
                        "application/json": {
                            "schema": {
                                "required": [
                                    "latitude",
                                    "longitude"
                                ],
                                "properties": {
                                    "latitude": {
                                        "type": "number",
                                        "format": "float"
                                    },
                                    "longitude": {
                                        "type": "number",
                                        "format": "float"
                                    }
                                },
                                "type": "object"
                            }
                        }
                    }
                },
                "responses": {
                    "200": {
                        "description": "Location updated"
                    }
                },
                "security": [
                    {
                        "bearerAuth": []
                    }
                ]
            }
        },
        "/api/user/nearby": {
            "get": {
                "tags": [
                    "User"
                ],
                "summary": "Get nearby users",
                "operationId": "c99abcfe7b21f9a1e211888f24a67500",
                "parameters": [
                    {
                        "name": "radius",
                        "in": "query",
                        "description": "Search radius in meters (default: 50)",
                        "schema": {
                            "type": "integer"
                        }
                    }
                ],
                "responses": {
                    "200": {
                        "description": "Nearby users retrieved"
                    }
                },
                "security": [
                    {
                        "bearerAuth": []
                    }
                ]
            }
        },
        "/api/user/account": {
            "delete": {
                "tags": [
                    "User"
                ],
                "summary": "Delete user account",
                "operationId": "7b3e247012567b8ba95773a7716c4811",
                "responses": {
                    "200": {
                        "description": "Account deleted"
                    }
                },
                "security": [
                    {
                        "bearerAuth": []
                    }
                ]
            }
        },
        "/api/user/ghost-mode": {
            "post": {
                "tags": [
                    "User"
                ],
                "summary": "Toggle Ghost Mode (Hide/Show from nearby users)",
                "operationId": "dba649840003ab00f67a2498108ff2be",
                "requestBody": {
                    "required": false,
                    "content": {
                        "application/json": {
                            "schema": {
                                "properties": {
                                    "is_visible": {
                                        "description": "true = visible, false = ghost mode",
                                        "type": "boolean"
                                    }
                                },
                                "type": "object"
                            }
                        }
                    }
                },
                "responses": {
                    "200": {
                        "description": "Ghost mode toggled",
                        "content": {
                            "application/json": {
                                "schema": {
                                    "properties": {
                                        "message": {
                                            "type": "string"
                                        },
                                        "is_visible": {
                                            "type": "boolean"
                                        },
                                        "status": {
                                            "type": "string",
                                            "example": "Ghost Mode ON"
                                        }
                                    },
                                    "type": "object"
                                }
                            }
                        }
                    }
                },
                "security": [
                    {
                        "bearerAuth": []
                    }
                ]
            }
        }
    },
    "components": {
        "securitySchemes": {
            "bearerAuth": {
                "type": "http",
                "scheme": "bearer",
                "bearerFormat": "JWT"
            }
        }
    },
    "tags": [
        {
            "name": "Authentication",
            "description": "Authentication"
        },
        {
            "name": "Block",
            "description": "Block"
        },
        {
            "name": "Likes",
            "description": "Likes"
        },
        {
            "name": "Messages",
            "description": "Messages"
        },
        {
            "name": "Reports",
            "description": "Reports"
        },
        {
            "name": "User",
            "description": "User"
        }
    ],
    "security": [
        {
            "bearerAuth": []
        }
    ]
}